ribonorma
