Metadata-Version: 2.1
Name: ribonorma
Version: 1.2
Summary: Implements additional normalisation methods for RNA Sequencing.
Home-page: https://github.com/Chokyotager/Ribonorma
Author: ChocoParrot (Hilbert L.), Kroppeb (Robbe P.)
Author-email: lachocoparrot@gmail.com
License: UNKNOWN
Project-URL: Bug Tracker, https://github.com/Chokyotager/Ribonorma/issues
Platform: UNKNOWN
Classifier: Programming Language :: Python :: 3
Classifier: License :: OSI Approved :: MIT License
Classifier: Operating System :: OS Independent
Requires-Python: >=3.6
License-File: LICENSE
